teleGate/__init__.py
teleGate/api.py
teleGate/bot.py
teleGate/config.py
teleGate/consts.py
teleGate/main.py
teleGate/subscribers.py
teleGate/utils.py
teleGate/version.py
teleGate-0.32.dist-info/LICENSE
teleGate-0.32.dist-info/METADATA
teleGate-0.32.dist-info/WHEEL
teleGate-0.32.dist-info/top_level.txt
teleGate-0.32.dist-info/RECORD
