Metadata-Version: 2.1
Name: teleGate
Version: 0.32
Summary: Simple logging-gate with http-api.
Home-page: https://gitlab.com/byaka/telegate
Author: BYaka
Author-email: byaka.life@gmail.com
License: UNKNOWN
Platform: UNKNOWN
Classifier: Programming Language :: Python :: 3
Classifier: License :: OSI Approved :: MIT License
Classifier: Operating System :: OS Independent
Requires-Python: >=3.6
Requires-Dist: telethon
Requires-Dist: aiohttp
